Metadata-Version: 2.1
Name: drf-jwt-auth
Version: 0.2.3
Summary: Django REST Framework JWT Authentication package enables to authenticate to Django REST Framework's API Views and ViewSets by using JWT (in header or as query param).
Home-page: https://gitlab.com/kas-factory/packages/drf-jwt-auth
Author: Alberto Casero
Author-email: alberto@kasfactory.net
License: COPYRIGHT
Platform: UNKNOWN
